README
setup.py
stormcloud/__init__.py
stormcloud.egg-info/PKG-INFO
stormcloud.egg-info/SOURCES.txt
stormcloud.egg-info/dependency_links.txt
stormcloud.egg-info/top_level.txt