Metadata-Version: 1.1
Name: stormcloud
Version: 0.0.1
Summary: Make testing downtime of third-party services easier.
Home-page: https://github.com/adamfast/stormcloud
Author: Adam Fast
Author-email: adamfast@gmail.com
License: BSD
Keywords: testing development
Platform: UNKNOWN
Classifier: Development Status :: 3 - Alpha
Classifier: Intended Audience :: Developers
Classifier: License :: OSI Approved :: BSD License
Classifier: Programming Language :: Python :: 2.7
